README.rst
setup.cfg
setup.py
synscan/__init__.py
synscan/comm.py
synscan/motors.py
synscan.egg-info/PKG-INFO
synscan.egg-info/SOURCES.txt
synscan.egg-info/dependency_links.txt
synscan.egg-info/entry_points.txt
synscan.egg-info/not-zip-safe
synscan.egg-info/requires.txt
synscan.egg-info/top_level.txt
synscan/scripts/__init__.py
synscan/scripts/cli.py