Metadata-Version: 2.1
Name: synscan
Version: 0.1.1
Summary: Pure python3 skywatcher synscan protocol
Home-page: https://github.com/nachoplus/pysynscan
Author: Nacho Mas
Author-email: mas.ignacio@gmail.com
License: GPL3
Download-URL: https://github.com/nachoplus/pysynscan/tarball/0.1
Keywords: robotic,telescope,skywatcher,synscan
Platform: UNKNOWN
Provides-Extra: test
